{
    "data": [
        {
            "ClientID": 2,
            "Guid": "9da5857e-cbc8-414e-a4d2-cccceb9fff06",
            "startDate": "2019-02-01",
            "endDate": "2021-06-18",
            "name": "Randgo",
            "manuallyScheduled": true,
            "expanded": true,
            "children": [
                {
                    "name": "tes wes",
                    "ProjectID": 56,
                    "Guid": "87a97172-802c-42ca-b83e-9a59f8bd3faf",
                    "startDate": "2021-05-03",
                    "endDate": "2021-06-18",
                    "manuallyScheduled": true,
                    "expanded": true,
                    "children": [
                        {
                            "id": 9,
                            "Guid": "6ea1a756-a651-4a17-b9d1-02fb7c26c103",
                            "startDate": "2021-05-03",
                            "endDate": "2021-06-18",
                            "name": "Test Ratets",
                            "completed": "NotCompleted",
                            "ClientID": 2,
                            "ProjectID": 56,
                            "SprintStatus": "New",
                            "manuallyScheduled": true,
                            "expanded": true,
                            "children": [
                                {
                                    "id": 165279,
                                    "TaskGuid": "5666c91a-cf0b-49ee-bfee-fc245b7f1550",
                                    "name": "New Task",
                                    "startDate": "2021-05-03",
                                    "endDate": "2021-06-18",
                                    "plannedHours": "20.0",
                                    "note": "Description for the new task",
                                    "status": "Assigned",
                                    "resource": 21,
                                    "priority": "Critical",
                                    "type": "Change Request",
                                    "ClientID": 2,
                                    "ProjectID": 56,
                                    "manuallyScheduled": true
                                },
                                {
                                    "id": 165282,
                                    "TaskGuid": "9c7bd264-2e21-4757-8f4c-dca7407117bf",
                                    "name": "Gert se stert",
                                    "startDate": "2021-05-03",
                                    "endDate": "2021-05-18",
                                    "plannedHours": "20.0",
                                    "note": "Description for the new task",
                                    "status": "Assigned",
                                    "resource": 21,
                                    "priority": "Urgent",
                                    "type": "Change Request",
                                    "ClientID": 2,
                                    "ProjectID": 56,
                                    "manuallyScheduled": true
                                }
                            ]
                        }
                    ]
                },
                {
                    "name": "johan se gesig skop",
                    "ProjectID": 57,
                    "Guid": "c41f4e62-d44a-47a2-b4a8-1eae4e07e292",
                    "startDate": "2019-02-01",
                    "endDate": "2021-06-11",
                    "manuallyScheduled": true,
                    "expanded": true,
                    "children": [
                        {
                            "id": 2,
                            "Guid": "264fe176-0c38-42d1-a8a0-a353bbda90df",
                            "startDate": "2019-02-01",
                            "endDate": "2021-06-11",
                            "name": "Johan ",
                            "completed": "NotCompleted",
                            "ClientID": 2,
                            "ProjectID": 57,
                            "SprintStatus": "New",
                            "manuallyScheduled": true,
                            "expanded": true,
                            "children": [
                                {
                                    "id": 165330,
                                    "TaskGuid": "8d405e0a-e4de-4c8e-b70c-626e6270d837",
                                    "name": "Test for new task update",
                                    "startDate": "2021-04-26",
                                    "endDate": "2021-06-11",
                                    "plannedHours": null,
                                    "note": null,
                                    "status": "Requested",
                                    "resource": 21,
                                    "priority": "Low",
                                    "type": "Change Request",
                                    "ClientID": 2,
                                    "ProjectID": 57,
                                    "manuallyScheduled": true
                                },
                                {
                                    "id": 1024,
                                    "TaskGuid": "27dabb82-834a-4f9c-885a-8d50ce4d0a47",
                                    "name": "zsvzsd",
                                    "startDate": "2019-03-03",
                                    "endDate": "2019-03-03",
                                    "plannedHours": "3.0",
                                    "note": "EK TOETS TRACKER",
                                    "status": "Assigned",
                                    "resource": 79,
                                    "priority": "Low",
                                    "type": "New Development",
                                    "ClientID": 2,
                                    "ProjectID": 57,
                                    "manuallyScheduled": true
                                },
                                {
                                    "id": 1023,
                                    "TaskGuid": "0d74fbb1-5698-47c6-ae58-6f56a3544cdb",
                                    "name": "xszdcvzsd",
                                    "startDate": "2019-02-01",
                                    "endDate": "2019-02-01",
                                    "plannedHours": "3.0",
                                    "note": "EK TOETS TRACKER",
                                    "status": "Assigned",
                                    "resource": 79,
                                    "priority": "Low",
                                    "type": "New Development",
                                    "ClientID": 2,
                                    "ProjectID": 57,
                                    "manuallyScheduled": true
                                }
                            ]
                        },
                        {
                            "id": 5,
                            "Guid": "11a9a891-f67f-44d0-8b4c-7558783c44ab",
                            "startDate": "2020-03-04",
                            "endDate": "2020-03-07",
                            "name": "fhgdgdfser",
                            "completed": "NotCompleted",
                            "ClientID": 2,
                            "ProjectID": 57,
                            "SprintStatus": "New",
                            "manuallyScheduled": true,
                            "expanded": true,
                            "children": [
                                {
                                    "id": 1032,
                                    "TaskGuid": "3c4207d6-4e67-4ecf-96e1-c9dc107778bd",
                                    "name": "#Tristan",
                                    "startDate": "2020-03-07",
                                    "endDate": "2020-03-07",
                                    "plannedHours": "4.0",
                                    "note": "\u003cp\u003easdasd\u003c/p\u003e",
                                    "status": "Assigned",
                                    "resource": 79,
                                    "priority": "Urgent",
                                    "type": "Report Request",
                                    "ClientID": 2,
                                    "ProjectID": 57,
                                    "manuallyScheduled": true
                                },
                                {
                                    "id": 165331,
                                    "TaskGuid": "eb6d908c-3191-4d03-b6a5-ce5bc7eae831",
                                    "name": "another one",
                                    "startDate": "2020-03-04",
                                    "endDate": "2020-03-04",
                                    "plannedHours": null,
                                    "note": null,
                                    "status": "Parked",
                                    "resource": 99,
                                    "priority": "Urgent",
                                    "type": "New Development",
                                    "ClientID": 2,
                                    "ProjectID": 57,
                                    "manuallyScheduled": true
                                }
                            ]
                        }
                    ]
                }
            ]
        }
    ]
}